{"status": 200, "code": 200, "time": 1634625298482, "message": "Th\u00e0nh c\u00f4ng", "data": [{"id": 3678, "createdAt": null, "nav": 10000.01, "navDate": "2017-08-30", "productId": 8}, {"id": 3677, "createdAt": null, "nav": 10001.0, "navDate": "2017-08-31", "productId": 8}, {"id": 3676, "createdAt": null, "nav": 9998.78, "navDate": "2017-09-05", "productId": 8}, {"id": 3675, "createdAt": null, "nav": 10014.09, "navDate": "2017-09-12", "productId": 8}, {"id": 3674, "createdAt": null, "nav": 10055.82, "navDate": "2017-09-19", "productId": 8}, {"id": 3673, "createdAt": null, "nav": 10063.1, "navDate": "2017-09-26", "productId": 8}, {"id": 3672, "createdAt": null, "nav": 10041.05, "navDate": "2017-09-30", "productId": 8}, {"id": 3671, "createdAt": null, "nav": 10051.06, "navDate": "2017-10-03", "productId": 8}, {"id": 3670, "createdAt": null, "nav": 10107.81, "navDate": "2017-10-10", "productId": 8}, {"id": 3669, "createdAt": null, "nav": 10112.87, "navDate": "2017-10-17", "productId": 8}, {"id": 3668, "createdAt": null, "nav": 10077.18, "navDate": "2017-10-24", "productId": 8}, {"id": 3666, "createdAt": null, "nav": 10103.44, "navDate": "2017-10-31", "productId": 8}, {"id": 3667, "createdAt": null, "nav": 10110.14, "navDate": "2017-10-31", "productId": 8}, {"id": 3665, "createdAt": null, "nav": 10200.69, "navDate": "2017-11-06", "productId": 8}, {"id": 3664, "createdAt": null, "nav": 10187.16, "navDate": "2017-11-13", "productId": 8}, {"id": 3663, "createdAt": null, "nav": 10237.49, "navDate": "2017-11-20", "productId": 8}, {"id": 3662, "createdAt": null, "nav": 10292.54, "navDate": "2017-11-27", "productId": 8}, {"id": 3661, "createdAt": null, "nav": 10334.32, "navDate": "2017-11-30", "productId": 8}, {"id": 3660, "createdAt": null, "nav": 10379.99, "navDate": "2017-12-04", "productId": 8}, {"id": 3659, "createdAt": null, "nav": 10268.71, "navDate": "2017-12-11", "productId": 8}, {"id": 3658, "createdAt": null, "nav": 10296.44, "navDate": "2017-12-18", "productId": 8}, {"id": 3657, "createdAt": null, "nav": 10336.41, "navDate": "2017-12-25", "productId": 8}, {"id": 3656, "createdAt": null, "nav": 10400.15, "navDate": "2017-12-31", "productId": 8}, {"id": 3655, "createdAt": null, "nav": 10401.2, "navDate": "2018-01-01", "productId": 8}, {"id": 3654, "createdAt": null, "nav": 10483.32, "navDate": "2018-01-08", "productId": 8}, {"id": 3653, "createdAt": null, "nav": 10544.05, "navDate": "2018-01-15", "productId": 8}, {"id": 3652, "createdAt": null, "nav": 10606.27, "navDate": "2018-01-22", "productId": 8}, {"id": 3651, "createdAt": null, "nav": 10594.42, "navDate": "2018-01-29", "productId": 8}, {"id": 3650, "createdAt": null, "nav": 10609.34, "navDate": "2018-01-31", "productId": 8}, {"id": 3649, "createdAt": null, "nav": 10493.69, "navDate": "2018-02-05", "productId": 8}, {"id": 3648, "createdAt": null, "nav": 10585.18, "navDate": "2018-02-12", "productId": 8}, {"id": 3647, "createdAt": null, "nav": 10747.01, "navDate": "2018-02-26", "productId": 8}, {"id": 3646, "createdAt": null, "nav": 10805.45, "navDate": "2018-02-28", "productId": 8}, {"id": 3645, "createdAt": null, "nav": 10764.48, "navDate": "2018-03-05", "productId": 8}, {"id": 3644, "createdAt": null, "nav": 10833.08, "navDate": "2018-03-12", "productId": 8}, {"id": 3643, "createdAt": null, "nav": 10898.44, "navDate": "2018-03-19", "productId": 8}, {"id": 3642, "createdAt": null, "nav": 10885.82, "navDate": "2018-03-26", "productId": 8}, {"id": 3641, "createdAt": null, "nav": 10909.22, "navDate": "2018-03-31", "productId": 8}, {"id": 3640, "createdAt": null, "nav": 10936.25, "navDate": "2018-04-02", "productId": 8}, {"id": 3639, "createdAt": null, "nav": 10954.98, "navDate": "2018-04-09", "productId": 8}, {"id": 3638, "createdAt": null, "nav": 10884.19, "navDate": "2018-04-16", "productId": 8}, {"id": 3637, "createdAt": null, "nav": 10831.39, "navDate": "2018-04-23", "productId": 8}, {"id": 3636, "createdAt": null, "nav": 10819.66, "navDate": "2018-04-30", "productId": 8}, {"id": 3635, "createdAt": null, "nav": 10862.08, "navDate": "2018-05-07", "productId": 8}, {"id": 3634, "createdAt": null, "nav": 10871.52, "navDate": "2018-05-14", "productId": 8}, {"id": 3633, "createdAt": null, "nav": 10856.77, "navDate": "2018-05-21", "productId": 8}, {"id": 3632, "createdAt": null, "nav": 10750.43, "navDate": "2018-05-28", "productId": 8}, {"id": 3631, "createdAt": null, "nav": 10855.3, "navDate": "2018-05-31", "productId": 8}, {"id": 3630, "createdAt": null, "nav": 10912.74, "navDate": "2018-06-04", "productId": 8}, {"id": 3629, "createdAt": null, "nav": 10926.99, "navDate": "2018-06-11", "productId": 8}, {"id": 3628, "createdAt": null, "nav": 10876.04, "navDate": "2018-06-18", "productId": 8}, {"id": 3627, "createdAt": null, "nav": 10892.21, "navDate": "2018-06-25", "productId": 8}, {"id": 3626, "createdAt": null, "nav": 10834.24, "navDate": "2018-06-30", "productId": 8}, {"id": 3625, "createdAt": null, "nav": 10815.54, "navDate": "2018-07-02", "productId": 8}, {"id": 3624, "createdAt": null, "nav": 10770.96, "navDate": "2018-07-09", "productId": 8}, {"id": 3623, "createdAt": null, "nav": 10788.08, "navDate": "2018-07-16", "productId": 8}, {"id": 3622, "createdAt": null, "nav": 10833.2, "navDate": "2018-07-23", "productId": 8}, {"id": 3621, "createdAt": null, "nav": 10858.67, "navDate": "2018-07-30", "productId": 8}, {"id": 3620, "createdAt": null, "nav": 10866.49, "navDate": "2018-07-31", "productId": 8}, {"id": 3619, "createdAt": null, "nav": 10868.35, "navDate": "2018-08-06", "productId": 8}, {"id": 3618, "createdAt": null, "nav": 10881.56, "navDate": "2018-08-13", "productId": 8}, {"id": 3617, "createdAt": null, "nav": 10893.71, "navDate": "2018-08-20", "productId": 8}, {"id": 3616, "createdAt": null, "nav": 10906.64, "navDate": "2018-08-27", "productId": 8}, {"id": 3615, "createdAt": null, "nav": 10910.49, "navDate": "2018-08-31", "productId": 8}, {"id": 3614, "createdAt": null, "nav": 10915.06, "navDate": "2018-09-03", "productId": 8}, {"id": 3613, "createdAt": null, "nav": 10920.74, "navDate": "2018-09-10", "productId": 8}, {"id": 3612, "createdAt": null, "nav": 10935.05, "navDate": "2018-09-17", "productId": 8}, {"id": 3611, "createdAt": null, "nav": 10941.7, "navDate": "2018-09-24", "productId": 8}, {"id": 3610, "createdAt": null, "nav": 10951.42, "navDate": "2018-09-30", "productId": 8}, {"id": 3609, "createdAt": null, "nav": 10963.03, "navDate": "2018-10-01", "productId": 8}, {"id": 3608, "createdAt": null, "nav": 10968.69, "navDate": "2018-10-08", "productId": 8}, {"id": 3607, "createdAt": null, "nav": 10977.83, "navDate": "2018-10-15", "productId": 8}, {"id": 3606, "createdAt": null, "nav": 10974.74, "navDate": "2018-10-22", "productId": 8}, {"id": 3605, "createdAt": null, "nav": 10966.07, "navDate": "2018-10-29", "productId": 8}, {"id": 3604, "createdAt": null, "nav": 10983.38, "navDate": "2018-10-31", "productId": 8}, {"id": 3603, "createdAt": null, "nav": 11003.0, "navDate": "2018-11-05", "productId": 8}, {"id": 3602, "createdAt": null, "nav": 11005.32, "navDate": "2018-11-12", "productId": 8}, {"id": 3601, "createdAt": null, "nav": 11020.14, "navDate": "2018-11-19", "productId": 8}, {"id": 3600, "createdAt": null, "nav": 11019.05, "navDate": "2018-11-26", "productId": 8}, {"id": 3599, "createdAt": null, "nav": 11026.78, "navDate": "2018-11-30", "productId": 8}, {"id": 3598, "createdAt": null, "nav": 11038.1, "navDate": "2018-12-03", "productId": 8}, {"id": 3597, "createdAt": null, "nav": 11045.17, "navDate": "2018-12-10", "productId": 8}, {"id": 3596, "createdAt": null, "nav": 11050.3, "navDate": "2018-12-12", "productId": 8}, {"id": 3595, "createdAt": null, "nav": 11060.76, "navDate": "2018-12-13", "productId": 8}, {"id": 3594, "createdAt": null, "nav": 11068.85, "navDate": "2018-12-16", "productId": 8}, {"id": 3593, "createdAt": null, "nav": 11067.61, "navDate": "2018-12-17", "productId": 8}, {"id": 3592, "createdAt": null, "nav": 11064.2, "navDate": "2018-12-18", "productId": 8}, {"id": 3591, "createdAt": null, "nav": 11063.21, "navDate": "2018-12-19", "productId": 8}, {"id": 3590, "createdAt": null, "nav": 11069.36, "navDate": "2018-12-20", "productId": 8}, {"id": 3589, "createdAt": null, "nav": 11078.49, "navDate": "2018-12-23", "productId": 8}, {"id": 3588, "createdAt": null, "nav": 11085.86, "navDate": "2018-12-24", "productId": 8}, {"id": 3587, "createdAt": null, "nav": 11079.22, "navDate": "2018-12-26", "productId": 8}, {"id": 3586, "createdAt": null, "nav": 11081.81, "navDate": "2018-12-27", "productId": 8}, {"id": 3585, "createdAt": null, "nav": 11088.13, "navDate": "2018-12-28", "productId": 8}, {"id": 3584, "createdAt": null, "nav": 11117.45, "navDate": "2019-01-02", "productId": 8}, {"id": 3583, "createdAt": null, "nav": 11118.83, "navDate": "2019-01-03", "productId": 8}, {"id": 3582, "createdAt": null, "nav": 11109.41, "navDate": "2019-01-04", "productId": 8}, {"id": 3581, "createdAt": null, "nav": 11116.07, "navDate": "2019-01-07", "productId": 8}, {"id": 3580, "createdAt": null, "nav": 11123.5, "navDate": "2019-01-08", "productId": 8}, {"id": 3579, "createdAt": null, "nav": 11126.42, "navDate": "2019-01-09", "productId": 8}, {"id": 3578, "createdAt": null, "nav": 11129.98, "navDate": "2019-01-10", "productId": 8}, {"id": 3577, "createdAt": null, "nav": 11133.51, "navDate": "2019-01-11", "productId": 8}, {"id": 3576, "createdAt": null, "nav": 11132.92, "navDate": "2019-01-14", "productId": 8}, {"id": 3575, "createdAt": null, "nav": 11140.43, "navDate": "2019-01-15", "productId": 8}, {"id": 3574, "createdAt": null, "nav": 11138.08, "navDate": "2019-01-16", "productId": 8}, {"id": 3573, "createdAt": null, "nav": 11137.88, "navDate": "2019-01-17", "productId": 8}, {"id": 3572, "createdAt": null, "nav": 11144.15, "navDate": "2019-01-18", "productId": 8}, {"id": 3571, "createdAt": null, "nav": 11145.75, "navDate": "2019-01-21", "productId": 8}, {"id": 3570, "createdAt": null, "nav": 11156.94, "navDate": "2019-01-22", "productId": 8}, {"id": 3569, "createdAt": null, "nav": 11158.24, "navDate": "2019-01-23", "productId": 8}, {"id": 3568, "createdAt": null, "nav": 11157.85, "navDate": "2019-01-24", "productId": 8}, {"id": 3567, "createdAt": null, "nav": 11161.35, "navDate": "2019-01-25", "productId": 8}, {"id": 3566, "createdAt": null, "nav": 11165.7, "navDate": "2019-01-28", "productId": 8}, {"id": 3565, "createdAt": null, "nav": 11167.7, "navDate": "2019-01-29", "productId": 8}, {"id": 3564, "createdAt": null, "nav": 11170.6, "navDate": "2019-01-30", "productId": 8}, {"id": 3563, "createdAt": null, "nav": 11171.86, "navDate": "2019-01-31", "productId": 8}, {"id": 3562, "createdAt": null, "nav": 11169.93, "navDate": "2019-02-01", "productId": 8}, {"id": 3561, "createdAt": null, "nav": 11186.7, "navDate": "2019-02-11", "productId": 8}, {"id": 3560, "createdAt": null, "nav": 11186.01, "navDate": "2019-02-12", "productId": 8}, {"id": 3559, "createdAt": null, "nav": 11185.96, "navDate": "2019-02-13", "productId": 8}, {"id": 3558, "createdAt": null, "nav": 11189.23, "navDate": "2019-02-14", "productId": 8}, {"id": 3557, "createdAt": null, "nav": 11190.59, "navDate": "2019-02-15", "productId": 8}, {"id": 3556, "createdAt": null, "nav": 11194.88, "navDate": "2019-02-18", "productId": 8}, {"id": 3555, "createdAt": null, "nav": 11196.71, "navDate": "2019-02-19", "productId": 8}, {"id": 3554, "createdAt": null, "nav": 11198.15, "navDate": "2019-02-20", "productId": 8}, {"id": 3553, "createdAt": null, "nav": 11200.1, "navDate": "2019-02-21", "productId": 8}, {"id": 3552, "createdAt": null, "nav": 11196.67, "navDate": "2019-02-22", "productId": 8}, {"id": 3551, "createdAt": null, "nav": 11206.79, "navDate": "2019-02-25", "productId": 8}, {"id": 3550, "createdAt": null, "nav": 11208.2, "navDate": "2019-02-26", "productId": 8}, {"id": 3549, "createdAt": null, "nav": 11214.48, "navDate": "2019-02-27", "productId": 8}, {"id": 3548, "createdAt": null, "nav": 11244.91, "navDate": "2019-02-28", "productId": 8}, {"id": 3547, "createdAt": null, "nav": 11237.95, "navDate": "2019-03-01", "productId": 8}, {"id": 3546, "createdAt": null, "nav": 11246.35, "navDate": "2019-03-04", "productId": 8}, {"id": 3545, "createdAt": null, "nav": 11245.81, "navDate": "2019-03-05", "productId": 8}, {"id": 3544, "createdAt": null, "nav": 11264.3, "navDate": "2019-03-06", "productId": 8}, {"id": 3543, "createdAt": null, "nav": 11268.09, "navDate": "2019-03-07", "productId": 8}, {"id": 3542, "createdAt": null, "nav": 11268.0, "navDate": "2019-03-08", "productId": 8}, {"id": 3541, "createdAt": null, "nav": 11274.75, "navDate": "2019-03-11", "productId": 8}, {"id": 3540, "createdAt": null, "nav": 11282.61, "navDate": "2019-03-12", "productId": 8}, {"id": 3539, "createdAt": null, "nav": 11269.18, "navDate": "2019-03-13", "productId": 8}, {"id": 3538, "createdAt": null, "nav": 11255.6, "navDate": "2019-03-14", "productId": 8}, {"id": 3537, "createdAt": null, "nav": 11274.12, "navDate": "2019-03-15", "productId": 8}, {"id": 3536, "createdAt": null, "nav": 11289.44, "navDate": "2019-03-18", "productId": 8}, {"id": 3535, "createdAt": null, "nav": 11283.68, "navDate": "2019-03-19", "productId": 8}, {"id": 3534, "createdAt": null, "nav": 11274.89, "navDate": "2019-03-20", "productId": 8}, {"id": 3533, "createdAt": null, "nav": 11278.58, "navDate": "2019-03-21", "productId": 8}, {"id": 3532, "createdAt": null, "nav": 11256.3, "navDate": "2019-03-22", "productId": 8}, {"id": 3531, "createdAt": null, "nav": 11274.25, "navDate": "2019-03-25", "productId": 8}, {"id": 3530, "createdAt": null, "nav": 11238.74, "navDate": "2019-03-26", "productId": 8}, {"id": 3529, "createdAt": null, "nav": 11245.02, "navDate": "2019-03-27", "productId": 8}, {"id": 3528, "createdAt": null, "nav": 11271.07, "navDate": "2019-03-28", "productId": 8}, {"id": 3527, "createdAt": null, "nav": 11281.44, "navDate": "2019-03-29", "productId": 8}, {"id": 3526, "createdAt": null, "nav": 11282.88, "navDate": "2019-04-01", "productId": 8}, {"id": 3525, "createdAt": null, "nav": 11290.96, "navDate": "2019-04-02", "productId": 8}, {"id": 3524, "createdAt": null, "nav": 11284.66, "navDate": "2019-04-03", "productId": 8}, {"id": 3523, "createdAt": null, "nav": 11299.41, "navDate": "2019-04-04", "productId": 8}, {"id": 3522, "createdAt": null, "nav": 11305.89, "navDate": "2019-04-05", "productId": 8}, {"id": 3521, "createdAt": null, "nav": 11296.7, "navDate": "2019-04-08", "productId": 8}, {"id": 3520, "createdAt": null, "nav": 11308.84, "navDate": "2019-04-09", "productId": 8}, {"id": 3519, "createdAt": null, "nav": 11307.39, "navDate": "2019-04-10", "productId": 8}, {"id": 3518, "createdAt": null, "nav": 11301.08, "navDate": "2019-04-11", "productId": 8}, {"id": 3517, "createdAt": null, "nav": 11307.59, "navDate": "2019-04-12", "productId": 8}, {"id": 3516, "createdAt": null, "nav": 11320.99, "navDate": "2019-04-16", "productId": 8}, {"id": 3515, "createdAt": null, "nav": 11326.4, "navDate": "2019-04-17", "productId": 8}, {"id": 3514, "createdAt": null, "nav": 11297.03, "navDate": "2019-04-18", "productId": 8}, {"id": 3513, "createdAt": null, "nav": 11276.97, "navDate": "2019-04-19", "productId": 8}, {"id": 3512, "createdAt": null, "nav": 11274.06, "navDate": "2019-04-22", "productId": 8}, {"id": 3511, "createdAt": null, "nav": 11267.04, "navDate": "2019-04-23", "productId": 8}, {"id": 3510, "createdAt": null, "nav": 11262.97, "navDate": "2019-04-24", "productId": 8}, {"id": 3509, "createdAt": null, "nav": 11297.04, "navDate": "2019-04-25", "productId": 8}, {"id": 3508, "createdAt": null, "nav": 11291.41, "navDate": "2019-04-26", "productId": 8}, {"id": 3507, "createdAt": null, "nav": 11318.13, "navDate": "2019-05-02", "productId": 8}, {"id": 3506, "createdAt": null, "nav": 11300.32, "navDate": "2019-05-03", "productId": 8}, {"id": 3505, "createdAt": null, "nav": 11286.25, "navDate": "2019-05-06", "productId": 8}, {"id": 3504, "createdAt": null, "nav": 11284.05, "navDate": "2019-05-07", "productId": 8}, {"id": 3503, "createdAt": null, "nav": 11269.82, "navDate": "2019-05-08", "productId": 8}, {"id": 3502, "createdAt": null, "nav": 11267.18, "navDate": "2019-05-09", "productId": 8}, {"id": 3501, "createdAt": null, "nav": 11260.9, "navDate": "2019-05-10", "productId": 8}, {"id": 3500, "createdAt": null, "nav": 11268.42, "navDate": "2019-05-13", "productId": 8}, {"id": 3499, "createdAt": null, "nav": 11274.96, "navDate": "2019-05-14", "productId": 8}, {"id": 3498, "createdAt": null, "nav": 11291.33, "navDate": "2019-05-15", "productId": 8}, {"id": 3497, "createdAt": null, "nav": 11306.98, "navDate": "2019-05-16", "productId": 8}, {"id": 3496, "createdAt": null, "nav": 11293.51, "navDate": "2019-05-17", "productId": 8}, {"id": 3495, "createdAt": null, "nav": 11294.14, "navDate": "2019-05-20", "productId": 8}, {"id": 3494, "createdAt": null, "nav": 11308.68, "navDate": "2019-05-21", "productId": 8}, {"id": 3493, "createdAt": null, "nav": 11308.16, "navDate": "2019-05-22", "productId": 8}, {"id": 3492, "createdAt": null, "nav": 11313.53, "navDate": "2019-05-23", "productId": 8}, {"id": 3491, "createdAt": null, "nav": 11321.66, "navDate": "2019-05-24", "productId": 8}, {"id": 3490, "createdAt": null, "nav": 11321.84, "navDate": "2019-05-27", "productId": 8}, {"id": 3489, "createdAt": null, "nav": 11332.63, "navDate": "2019-05-28", "productId": 8}, {"id": 3488, "createdAt": null, "nav": 11347.86, "navDate": "2019-05-29", "productId": 8}, {"id": 3487, "createdAt": null, "nav": 11335.68, "navDate": "2019-05-30", "productId": 8}, {"id": 3486, "createdAt": null, "nav": 11339.36, "navDate": "2019-05-31", "productId": 8}, {"id": 3485, "createdAt": null, "nav": 11310.69, "navDate": "2019-06-03", "productId": 8}, {"id": 3484, "createdAt": null, "nav": 11278.71, "navDate": "2019-06-04", "productId": 8}, {"id": 3483, "createdAt": null, "nav": 11301.98, "navDate": "2019-06-05", "productId": 8}, {"id": 3482, "createdAt": null, "nav": 11309.85, "navDate": "2019-06-06", "productId": 8}, {"id": 3481, "createdAt": null, "nav": 11324.89, "navDate": "2019-06-07", "productId": 8}, {"id": 3480, "createdAt": null, "nav": 11383.84, "navDate": "2019-06-10", "productId": 8}, {"id": 3479, "createdAt": null, "nav": 11398.55, "navDate": "2019-06-11", "productId": 8}, {"id": 3478, "createdAt": null, "nav": 11400.41, "navDate": "2019-06-12", "productId": 8}, {"id": 3477, "createdAt": null, "nav": 11374.52, "navDate": "2019-06-13", "productId": 8}, {"id": 3476, "createdAt": null, "nav": 11368.96, "navDate": "2019-06-14", "productId": 8}, {"id": 3475, "createdAt": null, "nav": 11351.84, "navDate": "2019-06-17", "productId": 8}, {"id": 3474, "createdAt": null, "nav": 11356.33, "navDate": "2019-06-18", "productId": 8}, {"id": 3473, "createdAt": null, "nav": 11372.69, "navDate": "2019-06-19", "productId": 8}, {"id": 3472, "createdAt": null, "nav": 11380.14, "navDate": "2019-06-20", "productId": 8}, {"id": 3471, "createdAt": null, "nav": 11397.06, "navDate": "2019-06-21", "productId": 8}, {"id": 3470, "createdAt": null, "nav": 11400.98, "navDate": "2019-06-24", "productId": 8}, {"id": 3469, "createdAt": null, "nav": 11382.03, "navDate": "2019-06-25", "productId": 8}, {"id": 3468, "createdAt": null, "nav": 11371.57, "navDate": "2019-06-26", "productId": 8}, {"id": 3467, "createdAt": null, "nav": 11375.32, "navDate": "2019-06-27", "productId": 8}, {"id": 3466, "createdAt": null, "nav": 11348.44, "navDate": "2019-06-28", "productId": 8}, {"id": 3465, "createdAt": null, "nav": 11347.88, "navDate": "2019-07-01", "productId": 8}, {"id": 3464, "createdAt": null, "nav": 11391.02, "navDate": "2019-07-02", "productId": 8}, {"id": 3463, "createdAt": null, "nav": 11403.55, "navDate": "2019-07-03", "productId": 8}, {"id": 3462, "createdAt": null, "nav": 11392.1, "navDate": "2019-07-04", "productId": 8}, {"id": 3461, "createdAt": null, "nav": 11433.21, "navDate": "2019-07-05", "productId": 8}, {"id": 3460, "createdAt": null, "nav": 11433.56, "navDate": "2019-07-08", "productId": 8}, {"id": 3459, "createdAt": null, "nav": 11432.04, "navDate": "2019-07-09", "productId": 8}, {"id": 3458, "createdAt": null, "nav": 11426.78, "navDate": "2019-07-10", "productId": 8}, {"id": 3457, "createdAt": null, "nav": 11451.51, "navDate": "2019-07-11", "productId": 8}, {"id": 3456, "createdAt": null, "nav": 11461.76, "navDate": "2019-07-12", "productId": 8}, {"id": 3455, "createdAt": null, "nav": 11471.84, "navDate": "2019-07-15", "productId": 8}, {"id": 3454, "createdAt": null, "nav": 11466.85, "navDate": "2019-07-16", "productId": 8}, {"id": 3453, "createdAt": null, "nav": 11460.16, "navDate": "2019-07-17", "productId": 8}, {"id": 3452, "createdAt": null, "nav": 11461.04, "navDate": "2019-07-18", "productId": 8}, {"id": 3451, "createdAt": null, "nav": 11457.05, "navDate": "2019-07-19", "productId": 8}, {"id": 3450, "createdAt": null, "nav": 11477.07, "navDate": "2019-07-22", "productId": 8}, {"id": 3449, "createdAt": null, "nav": 11485.93, "navDate": "2019-07-23", "productId": 8}, {"id": 3448, "createdAt": null, "nav": 11486.36, "navDate": "2019-07-24", "productId": 8}, {"id": 3447, "createdAt": null, "nav": 11481.6, "navDate": "2019-07-25", "productId": 8}, {"id": 3446, "createdAt": null, "nav": 11473.64, "navDate": "2019-07-26", "productId": 8}, {"id": 3445, "createdAt": null, "nav": 11481.09, "navDate": "2019-07-29", "productId": 8}, {"id": 3444, "createdAt": null, "nav": 11474.3, "navDate": "2019-07-30", "productId": 8}, {"id": 3443, "createdAt": null, "nav": 11452.09, "navDate": "2019-07-31", "productId": 8}, {"id": 3442, "createdAt": null, "nav": 11471.2, "navDate": "2019-08-01", "productId": 8}, {"id": 3441, "createdAt": null, "nav": 11484.01, "navDate": "2019-08-02", "productId": 8}, {"id": 3440, "createdAt": null, "nav": 11487.27, "navDate": "2019-08-05", "productId": 8}, {"id": 3439, "createdAt": null, "nav": 11502.98, "navDate": "2019-08-06", "productId": 8}, {"id": 3438, "createdAt": null, "nav": 11497.22, "navDate": "2019-08-07", "productId": 8}, {"id": 3437, "createdAt": null, "nav": 11523.04, "navDate": "2019-08-08", "productId": 8}, {"id": 3436, "createdAt": null, "nav": 11522.41, "navDate": "2019-08-09", "productId": 8}, {"id": 3435, "createdAt": null, "nav": 11541.86, "navDate": "2019-08-12", "productId": 8}, {"id": 3434, "createdAt": null, "nav": 11556.25, "navDate": "2019-08-13", "productId": 8}, {"id": 3433, "createdAt": null, "nav": 11556.27, "navDate": "2019-08-14", "productId": 8}, {"id": 3432, "createdAt": null, "nav": 11571.18, "navDate": "2019-08-15", "productId": 8}, {"id": 3431, "createdAt": null, "nav": 11577.63, "navDate": "2019-08-16", "productId": 8}, {"id": 3430, "createdAt": null, "nav": 11572.99, "navDate": "2019-08-19", "productId": 8}, {"id": 3429, "createdAt": null, "nav": 11572.55, "navDate": "2019-08-20", "productId": 8}, {"id": 3428, "createdAt": null, "nav": 11590.67, "navDate": "2019-08-21", "productId": 8}, {"id": 3427, "createdAt": null, "nav": 11598.39, "navDate": "2019-08-22", "productId": 8}, {"id": 3426, "createdAt": null, "nav": 11591.62, "navDate": "2019-08-23", "productId": 8}, {"id": 3425, "createdAt": null, "nav": 11601.77, "navDate": "2019-08-26", "productId": 8}, {"id": 3424, "createdAt": null, "nav": 11606.82, "navDate": "2019-08-27", "productId": 8}, {"id": 3423, "createdAt": null, "nav": 11586.5, "navDate": "2019-08-28", "productId": 8}, {"id": 3422, "createdAt": null, "nav": 11578.03, "navDate": "2019-08-29", "productId": 8}, {"id": 3421, "createdAt": null, "nav": 11602.26, "navDate": "2019-08-30", "productId": 8}, {"id": 3420, "createdAt": null, "nav": 11605.38, "navDate": "2019-08-31", "productId": 8}, {"id": 3419, "createdAt": null, "nav": 11608.6, "navDate": "2019-09-03", "productId": 8}, {"id": 3418, "createdAt": null, "nav": 11602.11, "navDate": "2019-09-04", "productId": 8}, {"id": 3417, "createdAt": null, "nav": 11607.34, "navDate": "2019-09-05", "productId": 8}, {"id": 3416, "createdAt": null, "nav": 11596.28, "navDate": "2019-09-06", "productId": 8}, {"id": 3415, "createdAt": null, "nav": 11605.34, "navDate": "2019-09-09", "productId": 8}, {"id": 3414, "createdAt": null, "nav": 11615.57, "navDate": "2019-09-10", "productId": 8}, {"id": 3413, "createdAt": null, "nav": 11620.07, "navDate": "2019-09-11", "productId": 8}, {"id": 3412, "createdAt": null, "nav": 11624.62, "navDate": "2019-09-12", "productId": 8}, {"id": 3411, "createdAt": null, "nav": 11653.89, "navDate": "2019-09-13", "productId": 8}, {"id": 3410, "createdAt": null, "nav": 11687.27, "navDate": "2019-09-16", "productId": 8}, {"id": 3409, "createdAt": null, "nav": 11701.83, "navDate": "2019-09-17", "productId": 8}, {"id": 3408, "createdAt": null, "nav": 11697.56, "navDate": "2019-09-18", "productId": 8}, {"id": 3407, "createdAt": null, "nav": 11689.91, "navDate": "2019-09-19", "productId": 8}, {"id": 3406, "createdAt": null, "nav": 11706.63, "navDate": "2019-09-20", "productId": 8}, {"id": 3405, "createdAt": null, "nav": 11713.1, "navDate": "2019-09-23", "productId": 8}, {"id": 3404, "createdAt": null, "nav": 11691.52, "navDate": "2019-09-24", "productId": 8}, {"id": 3403, "createdAt": null, "nav": 11688.45, "navDate": "2019-09-25", "productId": 8}, {"id": 3402, "createdAt": null, "nav": 11714.34, "navDate": "2019-09-26", "productId": 8}, {"id": 3401, "createdAt": null, "nav": 11739.98, "navDate": "2019-09-27", "productId": 8}, {"id": 3400, "createdAt": null, "nav": 11750.29, "navDate": "2019-09-30", "productId": 8}, {"id": 3399, "createdAt": null, "nav": 11741.6, "navDate": "2019-10-01", "productId": 8}, {"id": 3398, "createdAt": null, "nav": 11766.81, "navDate": "2019-10-02", "productId": 8}, {"id": 3397, "createdAt": null, "nav": 11752.0, "navDate": "2019-10-03", "productId": 8}, {"id": 3396, "createdAt": null, "nav": 11751.25, "navDate": "2019-10-04", "productId": 8}, {"id": 3395, "createdAt": null, "nav": 11735.45, "navDate": "2019-10-07", "productId": 8}, {"id": 3394, "createdAt": null, "nav": 11708.17, "navDate": "2019-10-08", "productId": 8}, {"id": 3393, "createdAt": null, "nav": 11724.09, "navDate": "2019-10-09", "productId": 8}, {"id": 3392, "createdAt": null, "nav": 11722.52, "navDate": "2019-10-10", "productId": 8}, {"id": 3391, "createdAt": null, "nav": 11723.44, "navDate": "2019-10-11", "productId": 8}, {"id": 3390, "createdAt": null, "nav": 11739.12, "navDate": "2019-10-14", "productId": 8}, {"id": 3389, "createdAt": null, "nav": 11751.84, "navDate": "2019-10-15", "productId": 8}, {"id": 3388, "createdAt": null, "nav": 11755.08, "navDate": "2019-10-16", "productId": 8}, {"id": 3387, "createdAt": null, "nav": 11751.37, "navDate": "2019-10-17", "productId": 8}, {"id": 3386, "createdAt": null, "nav": 11740.86, "navDate": "2019-10-18", "productId": 8}, {"id": 3385, "createdAt": null, "nav": 11742.08, "navDate": "2019-10-21", "productId": 8}, {"id": 3384, "createdAt": null, "nav": 11722.79, "navDate": "2019-10-22", "productId": 8}, {"id": 3383, "createdAt": null, "nav": 11747.07, "navDate": "2019-10-23", "productId": 8}, {"id": 3382, "createdAt": null, "nav": 11738.08, "navDate": "2019-10-24", "productId": 8}, {"id": 3381, "createdAt": null, "nav": 11772.38, "navDate": "2019-10-25", "productId": 8}, {"id": 3380, "createdAt": null, "nav": 11765.8, "navDate": "2019-10-28", "productId": 8}, {"id": 3379, "createdAt": null, "nav": 11773.25, "navDate": "2019-10-29", "productId": 8}, {"id": 3378, "createdAt": null, "nav": 11774.95, "navDate": "2019-10-30", "productId": 8}, {"id": 3377, "createdAt": null, "nav": 11771.72, "navDate": "2019-10-31", "productId": 8}, {"id": 3376, "createdAt": null, "nav": 11769.49, "navDate": "2019-11-01", "productId": 8}, {"id": 3375, "createdAt": null, "nav": 11766.45, "navDate": "2019-11-04", "productId": 8}, {"id": 3374, "createdAt": null, "nav": 11774.48, "navDate": "2019-11-05", "productId": 8}, {"id": 3373, "createdAt": null, "nav": 11773.95, "navDate": "2019-11-06", "productId": 8}, {"id": 3372, "createdAt": null, "nav": 11774.06, "navDate": "2019-11-07", "productId": 8}, {"id": 3371, "createdAt": null, "nav": 11794.32, "navDate": "2019-11-08", "productId": 8}, {"id": 3370, "createdAt": null, "nav": 11789.84, "navDate": "2019-11-11", "productId": 8}, {"id": 3369, "createdAt": null, "nav": 11785.57, "navDate": "2019-11-12", "productId": 8}, {"id": 3368, "createdAt": null, "nav": 11798.7, "navDate": "2019-11-13", "productId": 8}, {"id": 3367, "createdAt": null, "nav": 11806.28, "navDate": "2019-11-14", "productId": 8}, {"id": 3366, "createdAt": null, "nav": 11769.49, "navDate": "2019-11-15", "productId": 8}, {"id": 3365, "createdAt": null, "nav": 11784.22, "navDate": "2019-11-18", "productId": 8}, {"id": 3364, "createdAt": null, "nav": 11763.9, "navDate": "2019-11-19", "productId": 8}, {"id": 3363, "createdAt": null, "nav": 11773.89, "navDate": "2019-11-20", "productId": 8}, {"id": 3362, "createdAt": null, "nav": 11752.27, "navDate": "2019-11-21", "productId": 8}, {"id": 3361, "createdAt": null, "nav": 11729.88, "navDate": "2019-11-22", "productId": 8}, {"id": 3360, "createdAt": null, "nav": 11718.78, "navDate": "2019-11-25", "productId": 8}, {"id": 3359, "createdAt": null, "nav": 11701.09, "navDate": "2019-11-26", "productId": 8}, {"id": 3358, "createdAt": null, "nav": 11722.6, "navDate": "2019-11-27", "productId": 8}, {"id": 3357, "createdAt": null, "nav": 11722.35, "navDate": "2019-11-28", "productId": 8}, {"id": 3356, "createdAt": null, "nav": 11697.04, "navDate": "2019-11-29", "productId": 8}, {"id": 3355, "createdAt": null, "nav": 11716.69, "navDate": "2019-11-30", "productId": 8}, {"id": 3354, "createdAt": null, "nav": 11718.25, "navDate": "2019-12-02", "productId": 8}, {"id": 3353, "createdAt": null, "nav": 11679.5, "navDate": "2019-12-03", "productId": 8}, {"id": 3352, "createdAt": null, "nav": 11694.93, "navDate": "2019-12-04", "productId": 8}, {"id": 3351, "createdAt": null, "nav": 11731.0, "navDate": "2019-12-05", "productId": 8}, {"id": 3350, "createdAt": null, "nav": 11710.58, "navDate": "2019-12-06", "productId": 8}, {"id": 3349, "createdAt": null, "nav": 11725.58, "navDate": "2019-12-09", "productId": 8}, {"id": 3348, "createdAt": null, "nav": 11720.8, "navDate": "2019-12-10", "productId": 8}, {"id": 3347, "createdAt": null, "nav": 11718.17, "navDate": "2019-12-11", "productId": 8}, {"id": 3346, "createdAt": null, "nav": 11741.66, "navDate": "2019-12-12", "productId": 8}, {"id": 3345, "createdAt": null, "nav": 11742.31, "navDate": "2019-12-13", "productId": 8}, {"id": 3344, "createdAt": null, "nav": 11742.63, "navDate": "2019-12-16", "productId": 8}, {"id": 3343, "createdAt": null, "nav": 11774.15, "navDate": "2019-12-17", "productId": 8}, {"id": 3342, "createdAt": null, "nav": 11721.97, "navDate": "2019-12-18", "productId": 8}, {"id": 3341, "createdAt": null, "nav": 11701.25, "navDate": "2019-12-19", "productId": 8}, {"id": 3340, "createdAt": null, "nav": 11710.64, "navDate": "2019-12-20", "productId": 8}, {"id": 3339, "createdAt": null, "nav": 11736.55, "navDate": "2019-12-23", "productId": 8}, {"id": 3338, "createdAt": null, "nav": 11721.32, "navDate": "2019-12-24", "productId": 8}, {"id": 3337, "createdAt": null, "nav": 11723.47, "navDate": "2019-12-25", "productId": 8}, {"id": 3336, "createdAt": null, "nav": 11748.87, "navDate": "2019-12-26", "productId": 8}, {"id": 3335, "createdAt": null, "nav": 11738.93, "navDate": "2019-12-27", "productId": 8}, {"id": 3334, "createdAt": null, "nav": 11757.97, "navDate": "2019-12-30", "productId": 8}, {"id": 3332, "createdAt": null, "nav": 11771.25, "navDate": "2019-12-31", "productId": 8}, {"id": 3333, "createdAt": null, "nav": 11772.91, "navDate": "2019-12-31", "productId": 8}, {"id": 3331, "createdAt": null, "nav": 11772.96, "navDate": "2020-01-02", "productId": 8}, {"id": 3330, "createdAt": null, "nav": 11806.81, "navDate": "2020-01-03", "productId": 8}, {"id": 5447, "createdAt": 1609898863635, "nav": 12186.59, "navDate": "2020-01-05", "productId": 8}, {"id": 3329, "createdAt": null, "nav": 12188.55, "navDate": "2020-01-06", "productId": 8}, {"id": 3328, "createdAt": null, "nav": 11779.3, "navDate": "2020-01-07", "productId": 8}, {"id": 3327, "createdAt": null, "nav": 11792.7, "navDate": "2020-01-08", "productId": 8}, {"id": 3326, "createdAt": null, "nav": 11744.23, "navDate": "2020-01-09", "productId": 8}, {"id": 3325, "createdAt": null, "nav": 11798.78, "navDate": "2020-01-10", "productId": 8}, {"id": 3324, "createdAt": null, "nav": 11796.77, "navDate": "2020-01-13", "productId": 8}, {"id": 3323, "createdAt": null, "nav": 11795.89, "navDate": "2020-01-14", "productId": 8}, {"id": 3322, "createdAt": null, "nav": 11821.83, "navDate": "2020-01-15", "productId": 8}, {"id": 3321, "createdAt": null, "nav": 11819.98, "navDate": "2020-01-16", "productId": 8}, {"id": 3320, "createdAt": null, "nav": 11825.03, "navDate": "2020-01-17", "productId": 8}, {"id": 3319, "createdAt": null, "nav": 11844.84, "navDate": "2020-01-20", "productId": 8}, {"id": 3318, "createdAt": null, "nav": 11863.71, "navDate": "2020-01-21", "productId": 8}, {"id": 3317, "createdAt": null, "nav": 11865.39, "navDate": "2020-01-22", "productId": 8}, {"id": 3316, "createdAt": null, "nav": 11892.11, "navDate": "2020-01-30", "productId": 8}, {"id": 3314, "createdAt": null, "nav": 11837.16, "navDate": "2020-01-31", "productId": 8}, {"id": 3315, "createdAt": null, "nav": 11772.5, "navDate": "2020-01-31", "productId": 8}, {"id": 3313, "createdAt": null, "nav": 11775.86, "navDate": "2020-02-03", "productId": 8}, {"id": 3312, "createdAt": null, "nav": 11740.53, "navDate": "2020-02-04", "productId": 8}, {"id": 3311, "createdAt": null, "nav": 11741.89, "navDate": "2020-02-05", "productId": 8}, {"id": 3310, "createdAt": null, "nav": 11739.58, "navDate": "2020-02-06", "productId": 8}, {"id": 3309, "createdAt": null, "nav": 11784.87, "navDate": "2020-02-07", "productId": 8}, {"id": 3308, "createdAt": null, "nav": 11773.59, "navDate": "2020-02-10", "productId": 8}, {"id": 3307, "createdAt": null, "nav": 11750.16, "navDate": "2020-02-11", "productId": 8}, {"id": 3306, "createdAt": null, "nav": 11764.61, "navDate": "2020-02-12", "productId": 8}, {"id": 3305, "createdAt": null, "nav": 11802.5, "navDate": "2020-02-13", "productId": 8}, {"id": 3304, "createdAt": null, "nav": 11796.58, "navDate": "2020-02-14", "productId": 8}, {"id": 3303, "createdAt": null, "nav": 11799.25, "navDate": "2020-02-17", "productId": 8}, {"id": 3302, "createdAt": null, "nav": 11802.31, "navDate": "2020-02-18", "productId": 8}, {"id": 3301, "createdAt": null, "nav": 11831.34, "navDate": "2020-02-19", "productId": 8}, {"id": 3300, "createdAt": null, "nav": 11840.2, "navDate": "2020-02-20", "productId": 8}, {"id": 3299, "createdAt": null, "nav": 11845.75, "navDate": "2020-02-21", "productId": 8}, {"id": 3298, "createdAt": null, "nav": 11824.87, "navDate": "2020-02-24", "productId": 8}, {"id": 3297, "createdAt": null, "nav": 11751.65, "navDate": "2020-02-25", "productId": 8}, {"id": 3296, "createdAt": null, "nav": 11783.61, "navDate": "2020-02-26", "productId": 8}, {"id": 3295, "createdAt": null, "nav": 11783.08, "navDate": "2020-02-27", "productId": 8}, {"id": 3294, "createdAt": null, "nav": 11806.34, "navDate": "2020-02-28", "productId": 8}, {"id": 3293, "createdAt": null, "nav": 11786.23, "navDate": "2020-02-29", "productId": 8}, {"id": 3292, "createdAt": null, "nav": 11787.93, "navDate": "2020-03-02", "productId": 8}, {"id": 3291, "createdAt": null, "nav": 11793.69, "navDate": "2020-03-03", "productId": 8}, {"id": 3290, "createdAt": null, "nav": 11799.92, "navDate": "2020-03-04", "productId": 8}, {"id": 3289, "createdAt": null, "nav": 11801.8, "navDate": "2020-03-05", "productId": 8}, {"id": 3288, "createdAt": null, "nav": 11794.38, "navDate": "2020-03-06", "productId": 8}, {"id": 3287, "createdAt": null, "nav": 11779.83, "navDate": "2020-03-09", "productId": 8}, {"id": 3286, "createdAt": null, "nav": 11704.84, "navDate": "2020-03-10", "productId": 8}, {"id": 3285, "createdAt": null, "nav": 11713.19, "navDate": "2020-03-11", "productId": 8}, {"id": 3284, "createdAt": null, "nav": 11665.75, "navDate": "2020-03-12", "productId": 8}, {"id": 3283, "createdAt": null, "nav": 11615.65, "navDate": "2020-03-13", "productId": 8}, {"id": 3282, "createdAt": null, "nav": 11599.28, "navDate": "2020-03-16", "productId": 8}, {"id": 3281, "createdAt": null, "nav": 11581.84, "navDate": "2020-03-17", "productId": 8}, {"id": 3280, "createdAt": null, "nav": 11584.19, "navDate": "2020-03-18", "productId": 8}, {"id": 3279, "createdAt": null, "nav": 11586.85, "navDate": "2020-03-19", "productId": 8}, {"id": 3278, "createdAt": null, "nav": 11589.37, "navDate": "2020-03-20", "productId": 8}, {"id": 3277, "createdAt": null, "nav": 11593.7, "navDate": "2020-03-23", "productId": 8}, {"id": 3276, "createdAt": null, "nav": 11593.56, "navDate": "2020-03-24", "productId": 8}, {"id": 3275, "createdAt": null, "nav": 11596.1, "navDate": "2020-03-25", "productId": 8}, {"id": 3274, "createdAt": null, "nav": 11598.52, "navDate": "2020-03-26", "productId": 8}, {"id": 3273, "createdAt": null, "nav": 11598.38, "navDate": "2020-03-27", "productId": 8}, {"id": 3272, "createdAt": null, "nav": 11591.17, "navDate": "2020-03-30", "productId": 8}, {"id": 3270, "createdAt": null, "nav": 11594.68, "navDate": "2020-03-31", "productId": 8}, {"id": 3271, "createdAt": null, "nav": 11592.26, "navDate": "2020-03-31", "productId": 8}, {"id": 3269, "createdAt": null, "nav": 11594.68, "navDate": "2020-04-01", "productId": 8}, {"id": 3268, "createdAt": null, "nav": 11598.29, "navDate": "2020-04-03", "productId": 8}, {"id": 3267, "createdAt": null, "nav": 11604.35, "navDate": "2020-04-06", "productId": 8}, {"id": 3266, "createdAt": null, "nav": 11606.46, "navDate": "2020-04-07", "productId": 8}, {"id": 3265, "createdAt": null, "nav": 11607.28, "navDate": "2020-04-08", "productId": 8}, {"id": 3264, "createdAt": null, "nav": 11611.3, "navDate": "2020-04-09", "productId": 8}, {"id": 3263, "createdAt": null, "nav": 11614.63, "navDate": "2020-04-10", "productId": 8}, {"id": 3262, "createdAt": null, "nav": 11618.06, "navDate": "2020-04-13", "productId": 8}, {"id": 3261, "createdAt": null, "nav": 11621.45, "navDate": "2020-04-14", "productId": 8}, {"id": 3260, "createdAt": null, "nav": 11621.72, "navDate": "2020-04-15", "productId": 8}, {"id": 3259, "createdAt": null, "nav": 11635.2, "navDate": "2020-04-16", "productId": 8}, {"id": 3258, "createdAt": null, "nav": 11637.74, "navDate": "2020-04-17", "productId": 8}, {"id": 3257, "createdAt": null, "nav": 11639.7, "navDate": "2020-04-20", "productId": 8}, {"id": 3256, "createdAt": null, "nav": 11648.21, "navDate": "2020-04-21", "productId": 8}, {"id": 3255, "createdAt": null, "nav": 11647.08, "navDate": "2020-04-22", "productId": 8}, {"id": 3254, "createdAt": null, "nav": 11651.72, "navDate": "2020-04-23", "productId": 8}, {"id": 3253, "createdAt": null, "nav": 11650.09, "navDate": "2020-04-24", "productId": 8}, {"id": 3252, "createdAt": null, "nav": 11656.05, "navDate": "2020-04-27", "productId": 8}, {"id": 3251, "createdAt": null, "nav": 11658.25, "navDate": "2020-04-28", "productId": 8}, {"id": 3250, "createdAt": null, "nav": 11659.21, "navDate": "2020-04-29", "productId": 8}, {"id": 3249, "createdAt": null, "nav": 11651.42, "navDate": "2020-04-30", "productId": 8}, {"id": 3248, "createdAt": null, "nav": 11657.0, "navDate": "2020-05-04", "productId": 8}, {"id": 3247, "createdAt": null, "nav": 11668.49, "navDate": "2020-05-05", "productId": 8}, {"id": 3246, "createdAt": null, "nav": 11669.96, "navDate": "2020-05-06", "productId": 8}, {"id": 3245, "createdAt": null, "nav": 11672.55, "navDate": "2020-05-07", "productId": 8}, {"id": 3244, "createdAt": null, "nav": 11674.02, "navDate": "2020-05-08", "productId": 8}, {"id": 3243, "createdAt": null, "nav": 11679.24, "navDate": "2020-05-11", "productId": 8}, {"id": 3242, "createdAt": null, "nav": 11681.58, "navDate": "2020-05-12", "productId": 8}, {"id": 3241, "createdAt": null, "nav": 11683.8, "navDate": "2020-05-13", "productId": 8}, {"id": 3240, "createdAt": null, "nav": 11683.06, "navDate": "2020-05-14", "productId": 8}, {"id": 3239, "createdAt": null, "nav": 11687.25, "navDate": "2020-05-15", "productId": 8}, {"id": 3238, "createdAt": null, "nav": 11691.83, "navDate": "2020-05-18", "productId": 8}, {"id": 3237, "createdAt": null, "nav": 11693.58, "navDate": "2020-05-19", "productId": 8}, {"id": 3236, "createdAt": null, "nav": 11696.15, "navDate": "2020-05-20", "productId": 8}, {"id": 3235, "createdAt": null, "nav": 11698.41, "navDate": "2020-05-21", "productId": 8}, {"id": 3234, "createdAt": null, "nav": 11701.21, "navDate": "2020-05-22", "productId": 8}, {"id": 3233, "createdAt": null, "nav": 11704.98, "navDate": "2020-05-25", "productId": 8}, {"id": 3232, "createdAt": null, "nav": 11707.16, "navDate": "2020-05-26", "productId": 8}, {"id": 3231, "createdAt": null, "nav": 11709.42, "navDate": "2020-05-27", "productId": 8}, {"id": 3230, "createdAt": null, "nav": 11707.73, "navDate": "2020-05-28", "productId": 8}, {"id": 3229, "createdAt": null, "nav": 11711.81, "navDate": "2020-05-29", "productId": 8}, {"id": 3228, "createdAt": null, "nav": 11717.8, "navDate": "2020-05-31", "productId": 8}, {"id": 3227, "createdAt": null, "nav": 11717.8, "navDate": "2020-06-01", "productId": 8}, {"id": 3226, "createdAt": null, "nav": 11720.68, "navDate": "2020-06-02", "productId": 8}, {"id": 3225, "createdAt": null, "nav": 11722.11, "navDate": "2020-06-03", "productId": 8}, {"id": 3224, "createdAt": null, "nav": 11716.18, "navDate": "2020-06-04", "productId": 8}, {"id": 3223, "createdAt": null, "nav": 11727.3, "navDate": "2020-06-05", "productId": 8}, {"id": 3222, "createdAt": null, "nav": 11731.79, "navDate": "2020-06-08", "productId": 8}, {"id": 3221, "createdAt": null, "nav": 11734.16, "navDate": "2020-06-09", "productId": 8}, {"id": 3220, "createdAt": null, "nav": 11737.29, "navDate": "2020-06-10", "productId": 8}, {"id": 3219, "createdAt": null, "nav": 11737.3, "navDate": "2020-06-11", "productId": 8}, {"id": 3218, "createdAt": null, "nav": 11738.13, "navDate": "2020-06-12", "productId": 8}, {"id": 3217, "createdAt": null, "nav": 11743.69, "navDate": "2020-06-15", "productId": 8}, {"id": 3216, "createdAt": null, "nav": 11750.54, "navDate": "2020-06-16", "productId": 8}, {"id": 3215, "createdAt": null, "nav": 11751.52, "navDate": "2020-06-17", "productId": 8}, {"id": 3214, "createdAt": null, "nav": 11753.1, "navDate": "2020-06-18", "productId": 8}, {"id": 3213, "createdAt": null, "nav": 11763.33, "navDate": "2020-06-22", "productId": 8}, {"id": 3212, "createdAt": null, "nav": 11765.74, "navDate": "2020-06-23", "productId": 8}, {"id": 3211, "createdAt": null, "nav": 11768.32, "navDate": "2020-06-24", "productId": 8}, {"id": 3210, "createdAt": null, "nav": 11766.94, "navDate": "2020-06-25", "productId": 8}, {"id": 3209, "createdAt": null, "nav": 11772.79, "navDate": "2020-06-26", "productId": 8}, {"id": 3208, "createdAt": null, "nav": 11777.45, "navDate": "2020-06-29", "productId": 8}, {"id": 3206, "createdAt": null, "nav": 11783.27, "navDate": "2020-06-30", "productId": 8}, {"id": 3207, "createdAt": null, "nav": 11782.57, "navDate": "2020-06-30", "productId": 8}, {"id": 3205, "createdAt": null, "nav": 11783.27, "navDate": "2020-07-01", "productId": 8}, {"id": 3204, "createdAt": null, "nav": 11784.8, "navDate": "2020-07-02", "productId": 8}, {"id": 3203, "createdAt": null, "nav": 11786.61, "navDate": "2020-07-03", "productId": 8}, {"id": 3202, "createdAt": null, "nav": 11790.5, "navDate": "2020-07-06", "productId": 8}, {"id": 3201, "createdAt": null, "nav": 11793.5, "navDate": "2020-07-07", "productId": 8}, {"id": 3200, "createdAt": null, "nav": 11794.78, "navDate": "2020-07-08", "productId": 8}, {"id": 3199, "createdAt": null, "nav": 11797.14, "navDate": "2020-07-09", "productId": 8}, {"id": 3198, "createdAt": null, "nav": 11799.66, "navDate": "2020-07-10", "productId": 8}, {"id": 3197, "createdAt": null, "nav": 11804.52, "navDate": "2020-07-13", "productId": 8}, {"id": 3196, "createdAt": null, "nav": 11807.73, "navDate": "2020-07-14", "productId": 8}, {"id": 3195, "createdAt": null, "nav": 11809.14, "navDate": "2020-07-15", "productId": 8}, {"id": 3194, "createdAt": null, "nav": 11810.32, "navDate": "2020-07-16", "productId": 8}, {"id": 3193, "createdAt": null, "nav": 11814.27, "navDate": "2020-07-17", "productId": 8}, {"id": 3192, "createdAt": null, "nav": 11822.14, "navDate": "2020-07-20", "productId": 8}, {"id": 3191, "createdAt": null, "nav": 11820.82, "navDate": "2020-07-21", "productId": 8}, {"id": 3190, "createdAt": null, "nav": 11824.73, "navDate": "2020-07-22", "productId": 8}, {"id": 3189, "createdAt": null, "nav": 11828.33, "navDate": "2020-07-23", "productId": 8}, {"id": 3188, "createdAt": null, "nav": 11827.24, "navDate": "2020-07-24", "productId": 8}, {"id": 3187, "createdAt": null, "nav": 11834.16, "navDate": "2020-07-27", "productId": 8}, {"id": 3186, "createdAt": null, "nav": 11837.1, "navDate": "2020-07-28", "productId": 8}, {"id": 3185, "createdAt": null, "nav": 11840.02, "navDate": "2020-07-29", "productId": 8}, {"id": 3184, "createdAt": null, "nav": 11840.38, "navDate": "2020-07-30", "productId": 8}, {"id": 3182, "createdAt": null, "nav": 11843.4, "navDate": "2020-07-31", "productId": 8}, {"id": 3183, "createdAt": null, "nav": 11841.91, "navDate": "2020-07-31", "productId": 8}, {"id": 3181, "createdAt": null, "nav": 11847.76, "navDate": "2020-08-03", "productId": 8}, {"id": 3180, "createdAt": null, "nav": 11852.79, "navDate": "2020-08-04", "productId": 8}, {"id": 3179, "createdAt": null, "nav": 11853.56, "navDate": "2020-08-05", "productId": 8}, {"id": 3178, "createdAt": null, "nav": 11853.93, "navDate": "2020-08-06", "productId": 8}, {"id": 3177, "createdAt": null, "nav": 11859.29, "navDate": "2020-08-07", "productId": 8}, {"id": 3176, "createdAt": null, "nav": 11862.7, "navDate": "2020-08-10", "productId": 8}, {"id": 3175, "createdAt": null, "nav": 11862.83, "navDate": "2020-08-11", "productId": 8}, {"id": 3174, "createdAt": null, "nav": 11866.06, "navDate": "2020-08-12", "productId": 8}, {"id": 3173, "createdAt": null, "nav": 11867.38, "navDate": "2020-08-13", "productId": 8}, {"id": 3172, "createdAt": null, "nav": 11869.57, "navDate": "2020-08-14", "productId": 8}, {"id": 3171, "createdAt": null, "nav": 11874.54, "navDate": "2020-08-17", "productId": 8}, {"id": 3170, "createdAt": null, "nav": 11876.48, "navDate": "2020-08-18", "productId": 8}, {"id": 3169, "createdAt": null, "nav": 11879.11, "navDate": "2020-08-19", "productId": 8}, {"id": 3168, "createdAt": null, "nav": 11879.61, "navDate": "2020-08-20", "productId": 8}, {"id": 3167, "createdAt": null, "nav": 11883.48, "navDate": "2020-08-21", "productId": 8}, {"id": 3166, "createdAt": null, "nav": 11889.75, "navDate": "2020-08-24", "productId": 8}, {"id": 3165, "createdAt": null, "nav": 11891.84, "navDate": "2020-08-25", "productId": 8}, {"id": 3164, "createdAt": null, "nav": 11894.29, "navDate": "2020-08-26", "productId": 8}, {"id": 3163, "createdAt": null, "nav": 11896.97, "navDate": "2020-08-27", "productId": 8}, {"id": 3162, "createdAt": null, "nav": 11898.9, "navDate": "2020-08-28", "productId": 8}, {"id": 3160, "createdAt": null, "nav": 11907.0, "navDate": "2020-08-31", "productId": 8}, {"id": 3161, "createdAt": null, "nav": 11906.36, "navDate": "2020-08-31", "productId": 8}, {"id": 3159, "createdAt": null, "nav": 11907.0, "navDate": "2020-09-01", "productId": 8}, {"id": 3158, "createdAt": null, "nav": 11913.97, "navDate": "2020-09-03", "productId": 8}, {"id": 3157, "createdAt": null, "nav": 11915.11, "navDate": "2020-09-04", "productId": 8}, {"id": 3156, "createdAt": null, "nav": 11921.28, "navDate": "2020-09-07", "productId": 8}, {"id": 3155, "createdAt": null, "nav": 11924.03, "navDate": "2020-09-08", "productId": 8}, {"id": 3154, "createdAt": null, "nav": 11925.09, "navDate": "2020-09-09", "productId": 8}, {"id": 3153, "createdAt": null, "nav": 11928.77, "navDate": "2020-09-10", "productId": 8}, {"id": 3152, "createdAt": null, "nav": 11929.56, "navDate": "2020-09-11", "productId": 8}, {"id": 3151, "createdAt": null, "nav": 11937.46, "navDate": "2020-09-14", "productId": 8}, {"id": 3150, "createdAt": null, "nav": 11939.7, "navDate": "2020-09-15", "productId": 8}, {"id": 3149, "createdAt": null, "nav": 11941.41, "navDate": "2020-09-16", "productId": 8}, {"id": 3148, "createdAt": null, "nav": 11943.53, "navDate": "2020-09-17", "productId": 8}, {"id": 3147, "createdAt": null, "nav": 11944.49, "navDate": "2020-09-18", "productId": 8}, {"id": 3146, "createdAt": null, "nav": 11951.63, "navDate": "2020-09-21", "productId": 8}, {"id": 3145, "createdAt": null, "nav": 11954.72, "navDate": "2020-09-22", "productId": 8}, {"id": 3144, "createdAt": null, "nav": 11957.73, "navDate": "2020-09-23", "productId": 8}, {"id": 3143, "createdAt": null, "nav": 11959.84, "navDate": "2020-09-24", "productId": 8}, {"id": 3142, "createdAt": null, "nav": 11961.54, "navDate": "2020-09-25", "productId": 8}, {"id": 3141, "createdAt": null, "nav": 11968.77, "navDate": "2020-09-28", "productId": 8}, {"id": 3140, "createdAt": null, "nav": 11969.54, "navDate": "2020-09-29", "productId": 8}, {"id": 3138, "createdAt": null, "nav": 11974.26, "navDate": "2020-09-30", "productId": 8}, {"id": 3139, "createdAt": null, "nav": 11973.24, "navDate": "2020-09-30", "productId": 8}, {"id": 3137, "createdAt": null, "nav": 11974.26, "navDate": "2020-10-01", "productId": 8}, {"id": 3136, "createdAt": null, "nav": 11978.74, "navDate": "2020-10-02", "productId": 8}, {"id": 3135, "createdAt": null, "nav": 11982.54, "navDate": "2020-10-05", "productId": 8}, {"id": 3134, "createdAt": null, "nav": 11987.63, "navDate": "2020-10-06", "productId": 8}, {"id": 3133, "createdAt": null, "nav": 11988.37, "navDate": "2020-10-07", "productId": 8}, {"id": 3132, "createdAt": null, "nav": 11990.37, "navDate": "2020-10-08", "productId": 8}, {"id": 3131, "createdAt": null, "nav": 11993.56, "navDate": "2020-10-09", "productId": 8}, {"id": 3130, "createdAt": null, "nav": 12001.61, "navDate": "2020-10-12", "productId": 8}, {"id": 3129, "createdAt": null, "nav": 12003.05, "navDate": "2020-10-13", "productId": 8}, {"id": 3128, "createdAt": null, "nav": 12004.79, "navDate": "2020-10-14", "productId": 8}, {"id": 3127, "createdAt": null, "nav": 12005.09, "navDate": "2020-10-15", "productId": 8}, {"id": 3126, "createdAt": null, "nav": 12010.37, "navDate": "2020-10-16", "productId": 8}, {"id": 3125, "createdAt": null, "nav": 12015.17, "navDate": "2020-10-19", "productId": 8}, {"id": 3124, "createdAt": null, "nav": 12018.56, "navDate": "2020-10-20", "productId": 8}, {"id": 3123, "createdAt": null, "nav": 12021.72, "navDate": "2020-10-21", "productId": 8}, {"id": 3122, "createdAt": null, "nav": 12021.52, "navDate": "2020-10-22", "productId": 8}, {"id": 3121, "createdAt": null, "nav": 12025.12, "navDate": "2020-10-23", "productId": 8}, {"id": 3120, "createdAt": null, "nav": 12032.06, "navDate": "2020-10-26", "productId": 8}, {"id": 3119, "createdAt": null, "nav": 12036.5, "navDate": "2020-10-27", "productId": 8}, {"id": 3118, "createdAt": null, "nav": 12038.76, "navDate": "2020-10-28", "productId": 8}, {"id": 3117, "createdAt": null, "nav": 12041.14, "navDate": "2020-10-29", "productId": 8}, {"id": 3116, "createdAt": null, "nav": 12041.6, "navDate": "2020-10-30", "productId": 8}, {"id": 3115, "createdAt": null, "nav": 12047.22, "navDate": "2020-10-31", "productId": 8}, {"id": 3114, "createdAt": null, "nav": 12049.51, "navDate": "2020-11-02", "productId": 8}, {"id": 5210, "createdAt": null, "nav": 12049.51, "navDate": "2020-11-02", "productId": 8}, {"id": 3113, "createdAt": null, "nav": 12050.77, "navDate": "2020-11-03", "productId": 8}, {"id": 5209, "createdAt": null, "nav": 12050.77, "navDate": "2020-11-03", "productId": 8}, {"id": 3112, "createdAt": null, "nav": 12054.9, "navDate": "2020-11-04", "productId": 8}, {"id": 5208, "createdAt": null, "nav": 12054.9, "navDate": "2020-11-04", "productId": 8}, {"id": 5207, "createdAt": null, "nav": 12054.22, "navDate": "2020-11-05", "productId": 8}, {"id": 5149, "createdAt": 1604648253196, "nav": 12058.53, "navDate": "2020-11-06", "productId": 8}, {"id": 5206, "createdAt": null, "nav": 12058.53, "navDate": "2020-11-06", "productId": 8}, {"id": 5156, "createdAt": 1604913863788, "nav": 12063.27, "navDate": "2020-11-09", "productId": 8}, {"id": 5205, "createdAt": null, "nav": 12063.27, "navDate": "2020-11-09", "productId": 8}, {"id": 5160, "createdAt": 1604998674665, "nav": 12065.01, "navDate": "2020-11-10", "productId": 8}, {"id": 5204, "createdAt": null, "nav": 12065.01, "navDate": "2020-11-10", "productId": 8}, {"id": 5168, "createdAt": 1605078140299, "nav": 12068.92, "navDate": "2020-11-11", "productId": 8}, {"id": 5203, "createdAt": null, "nav": 12068.92, "navDate": "2020-11-11", "productId": 8}, {"id": 5171, "createdAt": 1605165359312, "nav": 12071.57, "navDate": "2020-11-12", "productId": 8}, {"id": 5202, "createdAt": null, "nav": 12071.57, "navDate": "2020-11-12", "productId": 8}, {"id": 5181, "createdAt": 1605254641957, "nav": 12072.81, "navDate": "2020-11-13", "productId": 8}, {"id": 5242, "createdAt": 1605511311975, "nav": 12077.52, "navDate": "2020-11-16", "productId": 8}, {"id": 5246, "createdAt": 1605599622445, "nav": 12077.82, "navDate": "2020-11-17", "productId": 8}, {"id": 5253, "createdAt": 1605684569682, "nav": 12080.89, "navDate": "2020-11-18", "productId": 8}, {"id": 5260, "createdAt": 1605771361423, "nav": 12082.82, "navDate": "2020-11-19", "productId": 8}, {"id": 5268, "createdAt": 1605861624932, "nav": 12085.74, "navDate": "2020-11-20", "productId": 8}, {"id": 5272, "createdAt": 1606115314432, "nav": 12091.48, "navDate": "2020-11-23", "productId": 8}, {"id": 5276, "createdAt": 1606212952297, "nav": 12094.04, "navDate": "2020-11-24", "productId": 8}, {"id": 5284, "createdAt": 1606295933623, "nav": 12097.15, "navDate": "2020-11-25", "productId": 8}, {"id": 5288, "createdAt": 1606376109795, "nav": 12097.15, "navDate": "2020-11-26", "productId": 8}, {"id": 5298, "createdAt": 1606468880434, "nav": 12100.5, "navDate": "2020-11-27", "productId": 8}, {"id": 5303, "createdAt": 1606719057531, "nav": 12107.37, "navDate": "2020-11-30", "productId": 8}, {"id": 5307, "createdAt": 1606815659667, "nav": 12109.25, "navDate": "2020-12-01", "productId": 8}, {"id": 5315, "createdAt": 1606896925000, "nav": 12111.74, "navDate": "2020-12-02", "productId": 8}, {"id": 5320, "createdAt": 1606981726221, "nav": 12114.26, "navDate": "2020-12-03", "productId": 8}, {"id": 5329, "createdAt": 1607072309988, "nav": 12116.02, "navDate": "2020-12-04", "productId": 8}, {"id": 5333, "createdAt": 1607329813914, "nav": 12122.25, "navDate": "2020-12-07", "productId": 8}, {"id": 5337, "createdAt": 1607411025039, "nav": 12124.79, "navDate": "2020-12-08", "productId": 8}, {"id": 5345, "createdAt": 1607500804972, "nav": 12126.98, "navDate": "2020-12-09", "productId": 8}, {"id": 5349, "createdAt": 1607586296641, "nav": 12128.61, "navDate": "2020-12-10", "productId": 8}, {"id": 5357, "createdAt": 1607670150903, "nav": 12130.84, "navDate": "2020-12-11", "productId": 8}, {"id": 5363, "createdAt": 1607937053200, "nav": 12137.68, "navDate": "2020-12-14", "productId": 8}, {"id": 5372, "createdAt": 1608101336538, "nav": 12142.1, "navDate": "2020-12-16", "productId": 8}, {"id": 5376, "createdAt": 1608188608669, "nav": 12144.74, "navDate": "2020-12-17", "productId": 8}, {"id": 5385, "createdAt": 1608274889160, "nav": 12146.57, "navDate": "2020-12-18", "productId": 8}, {"id": 5392, "createdAt": 1608628449241, "nav": 12155.37, "navDate": "2020-12-22", "productId": 8}, {"id": 5400, "createdAt": 1608709488318, "nav": 12158.14, "navDate": "2020-12-23", "productId": 8}, {"id": 5402, "createdAt": 1608795033878, "nav": 12160.11, "navDate": "2020-12-24", "productId": 8}, {"id": 5413, "createdAt": 1608884082658, "nav": 12162.2, "navDate": "2020-12-25", "productId": 8}, {"id": 5418, "createdAt": 1609144963752, "nav": 12169.37, "navDate": "2020-12-28", "productId": 8}, {"id": 5422, "createdAt": 1609228501720, "nav": 12171.77, "navDate": "2020-12-29", "productId": 8}, {"id": 5430, "createdAt": 1609312397712, "nav": 12173.55, "navDate": "2020-12-30", "productId": 8}, {"id": 5436, "createdAt": 1609406355273, "nav": 12176.39, "navDate": "2020-12-31", "productId": 8}, {"id": 5440, "createdAt": 1609752257750, "nav": 12184.44, "navDate": "2021-01-04", "productId": 8}, {"id": 5460, "createdAt": 1610013996337, "nav": 12190.53, "navDate": "2021-01-07", "productId": 8}, {"id": 5464, "createdAt": 1610096788675, "nav": 12192.53, "navDate": "2021-01-08", "productId": 8}, {"id": 5467, "createdAt": 1610358569236, "nav": 12199.22, "navDate": "2021-01-11", "productId": 8}, {"id": 5473, "createdAt": 1610444246854, "nav": 12201.21, "navDate": "2021-01-12", "productId": 8}, {"id": 5482, "createdAt": 1610524114260, "nav": 12203.42, "navDate": "2021-01-13", "productId": 8}, {"id": 5486, "createdAt": 1610608856848, "nav": 12205.36, "navDate": "2021-01-14", "productId": 8}, {"id": 5496, "createdAt": 1610707058676, "nav": 12207.48, "navDate": "2021-01-15", "productId": 8}, {"id": 5501, "createdAt": 1610961789825, "nav": 12213.43, "navDate": "2021-01-18", "productId": 8}, {"id": 5505, "createdAt": 1611046139982, "nav": 12214.07, "navDate": "2021-01-19", "productId": 8}, {"id": 5513, "createdAt": 1611133361785, "nav": 12216.23, "navDate": "2021-01-20", "productId": 8}, {"id": 5517, "createdAt": 1611216716402, "nav": 12217.81, "navDate": "2021-01-21", "productId": 8}, {"id": 5524, "createdAt": 1611301861250, "nav": 12219.7, "navDate": "2021-01-22", "productId": 8}, {"id": 5530, "createdAt": 1611565328813, "nav": 12225.35, "navDate": "2021-01-25", "productId": 8}, {"id": 5534, "createdAt": 1611645256479, "nav": 12227.23, "navDate": "2021-01-26", "productId": 8}, {"id": 5542, "createdAt": 1611733892250, "nav": 12229.03, "navDate": "2021-01-27", "productId": 8}, {"id": 5547, "createdAt": 1611825112420, "nav": 12230.78, "navDate": "2021-01-28", "productId": 8}, {"id": 5555, "createdAt": 1611914487484, "nav": 12232.83, "navDate": "2021-01-29", "productId": 8}, {"id": 5560, "createdAt": 1612173474221, "nav": 12238.66, "navDate": "2021-02-01", "productId": 8}, {"id": 5564, "createdAt": 1612255220632, "nav": 12240.89, "navDate": "2021-02-02", "productId": 8}, {"id": 5572, "createdAt": 1612341101408, "nav": 12242.91, "navDate": "2021-02-03", "productId": 8}, {"id": 5577, "createdAt": 1612426007486, "nav": 12244.91, "navDate": "2021-02-04", "productId": 8}, {"id": 5585, "createdAt": 1612516009780, "nav": 12246.44, "navDate": "2021-02-05", "productId": 8}, {"id": 5591, "createdAt": 1612842141596, "nav": 12253.03, "navDate": "2021-02-08", "productId": 8}, {"id": 5596, "createdAt": 1612864967901, "nav": 12255.38, "navDate": "2021-02-09", "productId": 8}, {"id": 5602, "createdAt": 1613552660396, "nav": 12271.3, "navDate": "2021-02-17", "productId": 8}, {"id": 5612, "createdAt": 1613640487424, "nav": 12273.74, "navDate": "2021-02-18", "productId": 8}, {"id": 5619, "createdAt": 1613724466871, "nav": 12275.39, "navDate": "2021-02-19", "productId": 8}, {"id": 5623, "createdAt": 1613984271077, "nav": 12281.64, "navDate": "2021-02-22", "productId": 8}, {"id": 5627, "createdAt": 1614070720516, "nav": 12282.67, "navDate": "2021-02-23", "productId": 8}, {"id": 5633, "createdAt": 1614156428350, "nav": 12284.31, "navDate": "2021-02-24", "productId": 8}, {"id": 5640, "createdAt": 1614245076124, "nav": 12286.71, "navDate": "2021-02-25", "productId": 8}, {"id": 5647, "createdAt": 1614335382751, "nav": 12288.94, "navDate": "2021-02-26", "productId": 8}, {"id": 5651, "createdAt": 1614591301522, "nav": 12295.22, "navDate": "2021-03-01", "productId": 8}, {"id": 5655, "createdAt": 1614671001446, "nav": 12297.11, "navDate": "2021-03-02", "productId": 8}, {"id": 5662, "createdAt": 1614757260522, "nav": 12296.89, "navDate": "2021-03-03", "productId": 8}, {"id": 5670, "createdAt": 1614850017642, "nav": 12299.07, "navDate": "2021-03-04", "productId": 8}, {"id": 5677, "createdAt": 1615171249628, "nav": 12300.96, "navDate": "2021-03-05", "productId": 8}, {"id": 5681, "createdAt": 1615260289304, "nav": 12307.12, "navDate": "2021-03-08", "productId": 8}, {"id": 5685, "createdAt": 1615277141837, "nav": 12309.1, "navDate": "2021-03-09", "productId": 8}, {"id": 5697, "createdAt": 1615449022573, "nav": 12313.04, "navDate": "2021-03-11", "productId": 8}, {"id": 5704, "createdAt": 1615536709565, "nav": 12314.99, "navDate": "2021-03-12", "productId": 8}, {"id": 5708, "createdAt": 1615798571214, "nav": 12320.84, "navDate": "2021-03-15", "productId": 8}, {"id": 5712, "createdAt": 1615883630532, "nav": 12324.4, "navDate": "2021-03-16", "productId": 8}, {"id": 5720, "createdAt": 1615969647414, "nav": 12326.29, "navDate": "2021-03-17", "productId": 8}, {"id": 5724, "createdAt": 1616056258274, "nav": 12328.03, "navDate": "2021-03-18", "productId": 8}, {"id": 5733, "createdAt": 1616143229784, "nav": 12329.63, "navDate": "2021-03-19", "productId": 8}, {"id": 5738, "createdAt": 1616403546302, "nav": 12335.87, "navDate": "2021-03-22", "productId": 8}, {"id": 5741, "createdAt": 1616485771986, "nav": 12338.02, "navDate": "2021-03-23", "productId": 8}, {"id": 5753, "createdAt": 1616661967083, "nav": 12342.11, "navDate": "2021-03-25", "productId": 8}, {"id": 5765, "createdAt": 1617011649707, "nav": 12351.04, "navDate": "2021-03-29", "productId": 8}, {"id": 5769, "createdAt": 1617092870714, "nav": 12353.3, "navDate": "2021-03-30", "productId": 8}, {"id": 5778, "createdAt": 1617263818714, "nav": 12357.71, "navDate": "2021-04-01", "productId": 8}, {"id": 5786, "createdAt": 1617357386384, "nav": 12359.98, "navDate": "2021-04-02", "productId": 8}, {"id": 5791, "createdAt": 1617613345629, "nav": 12366.72, "navDate": "2021-04-05", "productId": 8}, {"id": 5795, "createdAt": 1617699706321, "nav": 12368.79, "navDate": "2021-04-06", "productId": 8}, {"id": 5801, "createdAt": 1617785233581, "nav": 12371.07, "navDate": "2021-04-07", "productId": 8}, {"id": 5805, "createdAt": 1617872755997, "nav": 12373.19, "navDate": "2021-04-08", "productId": 8}, {"id": 5817, "createdAt": 1618211227052, "nav": 12375.29, "navDate": "2021-04-09", "productId": 8}, {"id": 5821, "createdAt": 1618301505706, "nav": 12383.56, "navDate": "2021-04-13", "productId": 8}, {"id": 5829, "createdAt": 1618390653323, "nav": 12388.68, "navDate": "2021-04-14", "productId": 8}, {"id": 5833, "createdAt": 1618472124273, "nav": 12390.55, "navDate": "2021-04-15", "productId": 8}, {"id": 5840, "createdAt": 1618559203370, "nav": 12391.96, "navDate": "2021-04-16", "productId": 8}, {"id": 5846, "createdAt": 1618824402569, "nav": 12397.67, "navDate": "2021-04-19", "productId": 8}, {"id": 5850, "createdAt": 1618907685311, "nav": 12399.32, "navDate": "2021-04-20", "productId": 8}, {"id": 5858, "createdAt": 1619083956261, "nav": 12403.74, "navDate": "2021-04-22", "productId": 8}, {"id": 5865, "createdAt": 1619164037173, "nav": 12405.42, "navDate": "2021-04-23", "productId": 8}, {"id": 5872, "createdAt": 1619428545034, "nav": 12412.05, "navDate": "2021-04-26", "productId": 8}, {"id": 5879, "createdAt": 1619604629903, "nav": 12416.2, "navDate": "2021-04-28", "productId": 8}, {"id": 5884, "createdAt": 1619686378813, "nav": 12418.41, "navDate": "2021-04-29", "productId": 8}, {"id": 5889, "createdAt": 1620117238378, "nav": 12428.79, "navDate": "2021-05-04", "productId": 8}, {"id": 5899, "createdAt": 1620205730834, "nav": 12430.49, "navDate": "2021-05-05", "productId": 8}, {"id": 5902, "createdAt": 1620292016496, "nav": 12433.14, "navDate": "2021-05-06", "productId": 8}, {"id": 5910, "createdAt": 1620373724976, "nav": 12435.04, "navDate": "2021-05-07", "productId": 8}, {"id": 5915, "createdAt": 1620631669129, "nav": 12441.95, "navDate": "2021-05-10", "productId": 8}, {"id": 5921, "createdAt": 1620719868390, "nav": 12444.27, "navDate": "2021-05-11", "productId": 8}, {"id": 5929, "createdAt": 1620805273869, "nav": 12446.38, "navDate": "2021-05-12", "productId": 8}, {"id": 5933, "createdAt": 1620890356565, "nav": 12448.53, "navDate": "2021-05-13", "productId": 8}, {"id": 5941, "createdAt": 1620975922478, "nav": 12451.27, "navDate": "2021-05-14", "productId": 8}, {"id": 5945, "createdAt": 1621238713128, "nav": 12457.62, "navDate": "2021-05-17", "productId": 8}, {"id": 5949, "createdAt": 1621327125106, "nav": 12459.59, "navDate": "2021-05-18", "productId": 8}, {"id": 5957, "createdAt": 1621414129880, "nav": 12461.63, "navDate": "2021-05-19", "productId": 8}, {"id": 5959, "createdAt": 1621483063195, "nav": 12463.82, "navDate": "2021-05-20", "productId": 8}, {"id": 5969, "createdAt": 1621580891065, "nav": 12465.99, "navDate": "2021-05-21", "productId": 8}, {"id": 5973, "createdAt": 1621840695457, "nav": 12472.44, "navDate": "2021-05-24", "productId": 8}, {"id": 5979, "createdAt": 1621930138492, "nav": 12474.59, "navDate": "2021-05-25", "productId": 8}, {"id": 5985, "createdAt": 1622001374557, "nav": 12476.73, "navDate": "2021-05-26", "productId": 8}, {"id": 5989, "createdAt": 1622087341989, "nav": 12478.89, "navDate": "2021-05-27", "productId": 8}, {"id": 6002, "createdAt": 1622436128906, "nav": 12487.5, "navDate": "2021-05-31", "productId": 8}, {"id": 6008, "createdAt": 1622538290486, "nav": 12490.93, "navDate": "2021-06-01", "productId": 8}, {"id": 6016, "createdAt": 1622622463077, "nav": 12493.13, "navDate": "2021-06-02", "productId": 8}, {"id": 6020, "createdAt": 1622706939288, "nav": 12495.27, "navDate": "2021-06-03", "productId": 8}, {"id": 6174, "createdAt": 1622779924550, "nav": 12497.88, "navDate": "2021-06-04", "productId": 8}, {"id": 6183, "createdAt": 1623055610512, "nav": 12503.61, "navDate": "2021-06-07", "productId": 8}, {"id": 6187, "createdAt": 1623140800154, "nav": 12506.21, "navDate": "2021-06-08", "productId": 8}, {"id": 6193, "createdAt": 1623211845290, "nav": 12508.28, "navDate": "2021-06-09", "productId": 8}, {"id": 6201, "createdAt": 1623312594621, "nav": 12510.34, "navDate": "2021-06-10", "productId": 8}, {"id": 6206, "createdAt": 1623387925645, "nav": 12514.08, "navDate": "2021-06-11", "productId": 8}, {"id": 6213, "createdAt": 1623645778552, "nav": 12519.91, "navDate": "2021-06-14", "productId": 8}, {"id": 6219, "createdAt": 1623742416197, "nav": 12521.93, "navDate": "2021-06-15", "productId": 8}, {"id": 6224, "createdAt": 1623816156824, "nav": 12524.46, "navDate": "2021-06-16", "productId": 8}, {"id": 6231, "createdAt": 1623905788197, "nav": 12525.91, "navDate": "2021-06-17", "productId": 8}, {"id": 6240, "createdAt": 1624004610782, "nav": 12528.67, "navDate": "2021-06-18", "productId": 8}, {"id": 6245, "createdAt": 1624248988513, "nav": 12535.47, "navDate": "2021-06-21", "productId": 8}, {"id": 6251, "createdAt": 1624346604814, "nav": 12537.4, "navDate": "2021-06-22", "productId": 8}, {"id": 6256, "createdAt": 1624420544796, "nav": 12538.84, "navDate": "2021-06-23", "productId": 8}, {"id": 6265, "createdAt": 1624524183145, "nav": 12540.86, "navDate": "2021-06-24", "productId": 8}, {"id": 6273, "createdAt": 1624611876643, "nav": 12542.9, "navDate": "2021-06-25", "productId": 8}, {"id": 6277, "createdAt": 1624853124066, "nav": 12548.61, "navDate": "2021-06-28", "productId": 8}, {"id": 6283, "createdAt": 1624952615222, "nav": 12550.76, "navDate": "2021-06-29", "productId": 8}, {"id": 6291, "createdAt": 1625038479623, "nav": 12552.87, "navDate": "2021-06-30", "productId": 8}, {"id": 6297, "createdAt": 1625128846911, "nav": 12557.74, "navDate": "2021-07-01", "productId": 8}, {"id": 6302, "createdAt": 1625198529022, "nav": 12559.84, "navDate": "2021-07-02", "productId": 8}, {"id": 6311, "createdAt": 1625481278816, "nav": 12565.66, "navDate": "2021-07-05", "productId": 8}, {"id": 6315, "createdAt": 1625559230645, "nav": 12567.17, "navDate": "2021-07-06", "productId": 8}, {"id": 6321, "createdAt": 1625630947653, "nav": 12569.43, "navDate": "2021-07-07", "productId": 8}, {"id": 6327, "createdAt": 1625716651221, "nav": 12571.37, "navDate": "2021-07-08", "productId": 8}, {"id": 6334, "createdAt": 1625803660163, "nav": 12574.96, "navDate": "2021-07-09", "productId": 8}, {"id": 6341, "createdAt": 1626062799630, "nav": 12580.91, "navDate": "2021-07-12", "productId": 8}, {"id": 6915, "createdAt": 1626164179912, "nav": 12583.0, "navDate": "2021-07-13", "productId": 8}, {"id": 6922, "createdAt": 1626234477920, "nav": 12585.11, "navDate": "2021-07-14", "productId": 8}, {"id": 6930, "createdAt": 1626323111146, "nav": 12587.24, "navDate": "2021-07-15", "productId": 8}, {"id": 6937, "createdAt": 1626409945791, "nav": 12589.37, "navDate": "2021-07-16", "productId": 8}, {"id": 6944, "createdAt": 1626669328826, "nav": 12593.12, "navDate": "2021-07-19", "productId": 8}, {"id": 6950, "createdAt": 1626766961868, "nav": 12595.35, "navDate": "2021-07-20", "productId": 8}, {"id": 6956, "createdAt": 1626841963738, "nav": 12597.77, "navDate": "2021-07-21", "productId": 8}, {"id": 6965, "createdAt": 1626934099519, "nav": 12599.87, "navDate": "2021-07-22", "productId": 8}, {"id": 6972, "createdAt": 1627015677256, "nav": 12602.0, "navDate": "2021-07-23", "productId": 8}, {"id": 6981, "createdAt": 1627285241260, "nav": 12608.51, "navDate": "2021-07-26", "productId": 8}, {"id": 6983, "createdAt": 1627359038152, "nav": 12612.91, "navDate": "2021-07-27", "productId": 8}, {"id": 6990, "createdAt": 1627457500316, "nav": 12614.95, "navDate": "2021-07-28", "productId": 8}, {"id": 7000, "createdAt": 1627543913586, "nav": 12617.01, "navDate": "2021-07-29", "productId": 8}, {"id": 7010, "createdAt": 1627635308365, "nav": 12619.61, "navDate": "2021-07-30", "productId": 8}, {"id": 7014, "createdAt": 1627895005486, "nav": 12625.73, "navDate": "2021-08-02", "productId": 8}, {"id": 7020, "createdAt": 1627979638409, "nav": 12627.77, "navDate": "2021-08-03", "productId": 8}, {"id": 7027, "createdAt": 1628065027879, "nav": 12629.92, "navDate": "2021-08-04", "productId": 8}, {"id": 7037, "createdAt": 1628152869415, "nav": 12632.08, "navDate": "2021-08-05", "productId": 8}, {"id": 7043, "createdAt": 1628236293179, "nav": 12634.35, "navDate": "2021-08-06", "productId": 8}, {"id": 7051, "createdAt": 1628496948048, "nav": 12640.49, "navDate": "2021-08-09", "productId": 8}, {"id": 7055, "createdAt": 1628582566215, "nav": 12642.55, "navDate": "2021-08-10", "productId": 8}, {"id": 7060, "createdAt": 1628669047367, "nav": 12644.55, "navDate": "2021-08-11", "productId": 8}, {"id": 7068, "createdAt": 1628757103198, "nav": 12646.59, "navDate": "2021-08-12", "productId": 8}, {"id": 7076, "createdAt": 1628830796979, "nav": 12648.61, "navDate": "2021-08-13", "productId": 8}, {"id": 7085, "createdAt": 1629104845234, "nav": 12655.17, "navDate": "2021-08-16", "productId": 8}, {"id": 7089, "createdAt": 1629187326414, "nav": 12657.29, "navDate": "2021-08-17", "productId": 8}, {"id": 7099, "createdAt": 1629278207372, "nav": 12659.42, "navDate": "2021-08-18", "productId": 8}, {"id": 7106, "createdAt": 1629357312389, "nav": 12661.65, "navDate": "2021-08-19", "productId": 8}, {"id": 7114, "createdAt": 1629444870509, "nav": 12663.76, "navDate": "2021-08-20", "productId": 8}, {"id": 7120, "createdAt": 1629707591515, "nav": 12669.87, "navDate": "2021-08-23", "productId": 8}, {"id": 7124, "createdAt": 1629794302516, "nav": 12671.77, "navDate": "2021-08-24", "productId": 8}, {"id": 7132, "createdAt": 1629875709775, "nav": 12673.78, "navDate": "2021-08-25", "productId": 8}, {"id": 7141, "createdAt": 1629967512346, "nav": 12675.9, "navDate": "2021-08-26", "productId": 8}, {"id": 7149, "createdAt": 1630051256065, "nav": 12678.02, "navDate": "2021-08-27", "productId": 8}, {"id": 7155, "createdAt": 1630309628817, "nav": 12685.36, "navDate": "2021-08-30", "productId": 8}, {"id": 7159, "createdAt": 1630395686399, "nav": 12687.39, "navDate": "2021-08-31", "productId": 8}, {"id": 7167, "createdAt": 1630483126733, "nav": 12689.51, "navDate": "2021-09-01", "productId": 8}, {"id": 7180, "createdAt": 1630922381655, "nav": 12700.34, "navDate": "2021-09-06", "productId": 8}, {"id": 7185, "createdAt": 1631001047879, "nav": 12700.73, "navDate": "2021-09-07", "productId": 8}, {"id": 7194, "createdAt": 1631092030620, "nav": 12702.89, "navDate": "2021-09-08", "productId": 8}, {"id": 7202, "createdAt": 1631172323644, "nav": 12704.68, "navDate": "2021-09-09", "productId": 8}, {"id": 7212, "createdAt": 1631248974575, "nav": 12706.83, "navDate": "2021-09-10", "productId": 8}, {"id": 7358, "createdAt": 1631520971823, "nav": 12713.21, "navDate": "2021-09-13", "productId": 8}, {"id": 7364, "createdAt": 1631606381016, "nav": 12715.32, "navDate": "2021-09-14", "productId": 8}, {"id": 7372, "createdAt": 1631697194479, "nav": 12717.42, "navDate": "2021-09-15", "productId": 8}, {"id": 8153, "createdAt": 1631779006350, "nav": 12719.52, "navDate": "2021-09-16", "productId": 8}, {"id": 8160, "createdAt": 1631853080653, "nav": 12721.63, "navDate": "2021-09-17", "productId": 8}, {"id": 8171, "createdAt": 1632119630369, "nav": 12727.96, "navDate": "2021-09-20", "productId": 8}, {"id": 8181, "createdAt": 1632206089544, "nav": 12729.77, "navDate": "2021-09-21", "productId": 8}, {"id": 8191, "createdAt": 1632298995876, "nav": 12731.74, "navDate": "2021-09-22", "productId": 8}, {"id": 8203, "createdAt": 1632370405966, "nav": 12733.95, "navDate": "2021-09-23", "productId": 8}, {"id": 8214, "createdAt": 1632459024112, "nav": 12736.17, "navDate": "2021-09-24", "productId": 8}, {"id": 8226, "createdAt": 1632717572255, "nav": 12742.93, "navDate": "2021-09-27", "productId": 8}, {"id": 8234, "createdAt": 1632809574601, "nav": 12745.17, "navDate": "2021-09-28", "productId": 8}, {"id": 8249, "createdAt": 1632906845939, "nav": 12746.46, "navDate": "2021-09-29", "productId": 8}, {"id": 8258, "createdAt": 1632992765999, "nav": 12748.68, "navDate": "2021-09-30", "productId": 8}, {"id": 8271, "createdAt": 1633069002166, "nav": 12750.91, "navDate": "2021-10-01", "productId": 8}, {"id": 8285, "createdAt": 1633336902564, "nav": 12757.65, "navDate": "2021-10-04", "productId": 8}, {"id": 8293, "createdAt": 1633424867583, "nav": 12759.89, "navDate": "2021-10-05", "productId": 8}, {"id": 8302, "createdAt": 1633501946950, "nav": 12762.13, "navDate": "2021-10-06", "productId": 8}, {"id": 8315, "createdAt": 1633597938950, "nav": 12764.32, "navDate": "2021-10-07", "productId": 8}, {"id": 8329, "createdAt": 1633681763491, "nav": 12766.5, "navDate": "2021-10-08", "productId": 8}, {"id": 8339, "createdAt": 1633944992501, "nav": 12773.08, "navDate": "2021-10-11", "productId": 8}, {"id": 8348, "createdAt": 1634028378317, "nav": 12775.26, "navDate": "2021-10-12", "productId": 8}, {"id": 8358, "createdAt": 1634117109901, "nav": 12777.43, "navDate": "2021-10-13", "productId": 8}, {"id": 8379, "createdAt": 1634206034066, "nav": 12779.61, "navDate": "2021-10-14", "productId": 8}, {"id": 8385, "createdAt": 1634289450646, "nav": 12781.73, "navDate": "2021-10-15", "productId": 8}, {"id": 8393, "createdAt": 1634534810034, "nav": 12788.32, "navDate": "2021-10-18", "productId": 8}, {"id": 8401, "createdAt": 1634623850669, "nav": 12789.85, "navDate": "2021-10-19", "productId": 8}], "extra": {"clientCode": "web", "clientVersion": "1626178835966", "cmsVersion": "1596193132376"}}